vconsoleprint/__init__.py
vconsoleprint/printer.py
vconsoleprint-1.0.2.dist-info/licenses/LICENSE
vconsoleprint-1.0.2.dist-info/METADATA
vconsoleprint-1.0.2.dist-info/WHEEL
vconsoleprint-1.0.2.dist-info/top_level.txt
vconsoleprint-1.0.2.dist-info/RECORD
