Metadata-Version: 2.4
Name: vconsoleprint
Version: 1.0.2
Summary: Auto-colored Python console print replacement
Home-page: https://pypi.org/project/vconsoleprint/
Author: Vansh Sharma
Author-email: vanshsharma7832@gmail.com
License: MIT
Requires-Python: >=3.6
License-File: LICENSE
Requires-Dist: termcolor
Dynamic: author
Dynamic: author-email
Dynamic: description
Dynamic: description-content-type
Dynamic: home-page
Dynamic: license
Dynamic: license-file
Dynamic: requires-dist
Dynamic: requires-python
Dynamic: summary
